mlops_propulsion_academy/__init__.py
mlops_propulsion_academy/command_line.py
mlops_propulsion_academy/mlops.py
mlops_propulsion_academy-1.4.data/scripts/install.sh
mlops_propulsion_academy-1.4.data/scripts/mlops_scripts
mlops_propulsion_academy-1.4.data/scripts/start.sh
mlops_propulsion_academy-1.4.data/scripts/update.sh
mlops_propulsion_academy-1.4.dist-info/METADATA
mlops_propulsion_academy-1.4.dist-info/WHEEL
mlops_propulsion_academy-1.4.dist-info/top_level.txt
mlops_propulsion_academy-1.4.dist-info/RECORD
