Metadata-Version: 2.1
Name: mlops-propulsion-academy
Version: 1.4
Summary: mlops_propulsion_academy
Home-page: UNKNOWN
Author: Daniele Roncaglioni
Author-email: danieler@propulsionacademy.com
License: MIT
Platform: UNKNOWN
